rssfilter/__init__.py
rssfilter/admin.py
rssfilter/migrations/0001_initial.py
rssfilter/migrations/__init__.py
rssfilter/models.py
rssfilter/settings.py
rssfilter/urls.py
rssfilter/utils.py
rssfilter/views.py
django_rss_filter-0.14.1.dist-info/licenses/LICENSE
django_rss_filter-0.14.1.dist-info/WHEEL
django_rss_filter-0.14.1.dist-info/METADATA
django_rss_filter-0.14.1.dist-info/RECORD
