Metadata-Version: 2.4
Name: django-rss-filter
Version: 0.14.1
Summary: Filter public RSS feeds, remove articles that contain certain keywords or categories.
Keywords: rss,atom,feed,filter,mute,django
Author: Kevin Renskers
Author-email: Kevin Renskers <kevin@loopwerk.io>
License-Expression: MIT
License-File: LICENSE
Classifier: License :: OSI Approved :: MIT License
Classifier: Development Status :: 5 - Production/Stable
Classifier: Intended Audience :: Developers
Classifier: Framework :: Django
Classifier: Framework :: Django :: 4.2
Classifier: Framework :: Django :: 5.0
Classifier: Framework :: Django :: 5.1
Classifier: Framework :: Django :: 5.2
Classifier: Framework :: Django :: 6.0
Classifier: Programming Language :: Python
Classifier: Programming Language :: Python :: 3.10
Classifier: Programming Language :: Python :: 3.11
Classifier: Programming Language :: Python :: 3.12
Classifier: Programming Language :: Python :: 3.13
Classifier: Programming Language :: Python :: 3.14
Classifier: Programming Language :: Python :: 3.15
Requires-Dist: django>=4.2.0
Requires-Dist: feedgen>=1.0.0
Requires-Dist: feedparser>=6.0.11
Requires-Dist: httpx>=0.28.1
Requires-Python: >=3.10
Project-URL: Homepage, https://github.com/loopwerk/django-rss-filter/
Project-URL: Issues, https://github.com/loopwerk/django-rss-filter/issues
Project-URL: Repository, https://github.com/loopwerk/django-rss-filter.git
